svv/__init__.py
svv/telemetry.py
svv/domain/__init__.py
svv/domain/domain.py
svv/domain/patch.py
svv/domain/weingarten.py
svv/domain/core/__init__.py
svv/domain/core/a_matrix.py
svv/domain/core/h_matrix.py
svv/domain/core/m_matrix.py
svv/domain/core/n_matrix.py
svv/domain/io/__init__.py
svv/domain/io/dmn.py
svv/domain/io/read.py
svv/domain/kernel/__init__.py
svv/domain/kernel/coordinate_system.py
svv/domain/kernel/cost.py
svv/domain/kernel/kernel.py
svv/domain/routines/__init__.py
svv/domain/routines/allocate.py
svv/domain/routines/boolean.py
svv/domain/routines/c_allocate.py
svv/domain/routines/c_allocate.pyx
svv/domain/routines/c_sample.py
svv/domain/routines/c_sample.pyx
svv/domain/routines/discretize.py
svv/domain/routines/tetgen_worker.py
svv/domain/routines/tetrahedralize.py
svv/domain/solver/__init__.py
svv/domain/solver/solver.py
svv/forest/__init__.py
svv/forest/forest.py
svv/forest/connect/__init__.py
svv/forest/connect/assign.py
svv/forest/connect/base.py
svv/forest/connect/base_connection.py
svv/forest/connect/bezier.py
svv/forest/connect/catmullrom.py
svv/forest/connect/connect.py
svv/forest/connect/curve.py
svv/forest/connect/forest_connection.py
svv/forest/connect/geodesic.py
svv/forest/connect/nurbs.py
svv/forest/connect/optimize.py
svv/forest/connect/tree_connection.py
svv/forest/connect/vessel_connection.py
svv/forest/export/__init__.py
svv/forest/export/export_solid.py
svv/forest/export/export_spline.py
svv/simulation/__init__.py
svv/simulation/boundary_conditions.py
svv/simulation/equation.py
svv/simulation/general_parameters.py
svv/simulation/linear_solver.py
svv/simulation/mesh.py
svv/simulation/output.py
svv/simulation/simulation.py
svv/simulation/fluid/__init__.py
svv/simulation/fluid/fluid_equation.py
svv/simulation/fluid/inflow/__init__.py
svv/simulation/fluid/inflow/waveform.py
svv/simulation/fluid/rom/__init__.py
svv/simulation/fluid/rom/one_d/__init__.py
svv/simulation/fluid/rom/one_d/centerlines.py
svv-0.0.43.dist-info/METADATA
svv-0.0.43.dist-info/WHEEL
svv-0.0.43.dist-info/top_level.txt
svv-0.0.43.dist-info/RECORD
